<annotation>
	<folder>collectedimages</folder>
	<filename>iloveyou.b62b31b4-9909-11ee-9feb-3b483b4687e5.jpg</filename>
	<path>/home/soham/SignLang/Tensorflow/workspace/images/collectedimages/iloveyou.b62b31b4-9909-11ee-9feb-3b483b4687e5.jpg</path>
	<source>
		<database>Unknown</database>
	</source>
	<size>
		<width>640</width>
		<height>480</height>
		<depth>3</depth>
	</size>
	<segmented>0</segmented>
	<object>
		<name>ILoveYou</name>
		<pose>Unspecified</pose>
		<truncated>0</truncated>
		<difficult>0</difficult>
		<bndbox>
			<xmin>383</xmin>
			<ymin>4</ymin>
			<xmax>578</xmax>
			<ymax>279</ymax>
		</bndbox>
	</object>
</annotation>
